<?xml version="1.0" encoding="utf-8"?>
<!DOCTYPE hibernate-mapping PUBLIC "-//Hibernate/Hibernate Mapping DTD 3.0//EN"
"http://hibernate.sourceforge.net/hibernate-mapping-3.0.dtd">


<hibernate-mapping>
	<class name="com.ff.domain.serviceOffering.ProductGroupServiceabilityDO" table="ff_d_product_group_srvcblty">
		<id name="prodGroupId" type="java.lang.Integer">
			<column name="PROD_GROUP_ID" />
			<generator class="native" />
		</id>
		<property name="progGroupCode" column="PROD_GROUP_CODE" type="java.lang.String"/>
		<property name="prodGroupName" column="PROD_GROUP_NAME" type="java.lang.String"/>
		<property name="status" column="STATUS" type="java.lang.String"/>
		<property name="dtToBranch" column="DT_TO_BRANCH" />
		<property name="isOriginUndefined" column="IS_ORIGIN_UNDEFINED" type="java.lang.String"/>
		 
	</class>
</hibernate-mapping>